console_images/__init__.py
console_images/to_ascii.py
console_images-0.0.4.dist-info/LICENSE
console_images-0.0.4.dist-info/METADATA
console_images-0.0.4.dist-info/WHEEL
console_images-0.0.4.dist-info/top_level.txt
console_images-0.0.4.dist-info/RECORD
