Metadata-Version: 2.1
Name: console-images
Version: 0.0.4
Summary: Colored console images and gifs
Home-page: UNKNOWN
Author: LedinecMing
Author-email: loliamalexxaxa@gmail.com
License: UNKNOWN
Platform: UNKNOWN
Classifier: Programming Language :: Python :: 3.8
Classifier: License :: OSI Approved :: Apache Software License
Classifier: Operating System :: OS Independent
Requires-Python: >=3.6
License-File: LICENSE
Requires-Dist: colorama
Requires-Dist: typing
Requires-Dist: pillow
